konoise-1.0.8.5.dist-info/METADATA
konoise-1.0.8.5.dist-info/RECORD
konoise-1.0.8.5.dist-info/top_level.txt
konoise-1.0.8.5.dist-info/WHEEL
konoise/utils.py
konoise/spliter.py
konoise/phoneme.py
konoise/__init__.py
konoise/yamin.py
konoise/segments.py
konoise/rust_generator.cpython-37m-x86_64-linux-gnu.so
konoise/generator.py
konoise/data/endwords.json
