Metadata-Version: 2.1
Name: konoise
Version: 1.0.8.5
Summary: Korean Noise Generator
Home-page: https://github.com/wisenut-research/konoise
Author: Eddie
Author-email: hkjeo13@gmail.com
License: MIT
Classifier: Intended Audience :: Developers
Classifier: Intended Audience :: Science/Research
Classifier: License :: OSI Approved :: MIT License
Classifier: Operating System :: OS Independent
Classifier: Programming Language :: Python :: 3
Requires-Python: >=3
Requires-Dist: tqdm
